AERO40041/__init__.py
AERO40041/competition.py
AERO40041/tests.py
AERO40041-0.0.13.dist-info/LICENSE
AERO40041-0.0.13.dist-info/METADATA
AERO40041-0.0.13.dist-info/WHEEL
AERO40041-0.0.13.dist-info/top_level.txt
AERO40041-0.0.13.dist-info/RECORD
